google_drive_to_sqlite/__init__.py
google_drive_to_sqlite/cli.py
google_drive_to_sqlite/utils.py
google_drive_to_sqlite-0.4.dist-info/LICENSE
google_drive_to_sqlite-0.4.dist-info/METADATA
google_drive_to_sqlite-0.4.dist-info/WHEEL
google_drive_to_sqlite-0.4.dist-info/entry_points.txt
google_drive_to_sqlite-0.4.dist-info/top_level.txt
google_drive_to_sqlite-0.4.dist-info/RECORD
