Metadata-Version: 2.1
Name: google-drive-to-sqlite
Version: 0.4
Summary: Create a SQLite database containing metadata from Google Drive
Home-page: https://github.com/simonw/google-drive-to-sqlite
Author: Simon Willison
License: Apache License, Version 2.0
Project-URL: Issues, https://github.com/simonw/google-drive-to-sqlite/issues
Project-URL: CI, https://github.com/simonw/google-drive-to-sqlite/actions
Project-URL: Changelog, https://github.com/simonw/google-drive-to-sqlite/releases
Platform: UNKNOWN
Requires-Python: >=3.6
License-File: LICENSE
Requires-Dist: click
Requires-Dist: httpx
Requires-Dist: sqlite-utils
Provides-Extra: test
Requires-Dist: pytest ; extra == 'test'
Requires-Dist: pytest-httpx ; extra == 'test'
Requires-Dist: pytest-mock ; extra == 'test'
Requires-Dist: cogapp ; extra == 'test'
